pyhht/__init__.py
pyhht/emd.py
pyhht/utils.py
pyhht/visualization.py
pyhht-0.1.0.dist-info/DESCRIPTION.rst
pyhht-0.1.0.dist-info/METADATA
pyhht-0.1.0.dist-info/RECORD
pyhht-0.1.0.dist-info/WHEEL
pyhht-0.1.0.dist-info/metadata.json
pyhht-0.1.0.dist-info/top_level.txt
