Metadata-Version: 2.0
Name: pyhht
Version: 0.1.0
Summary: UNKNOWN
Home-page: UNKNOWN
Author: Jaidev Deshpande
Author-email: deshpande.jaidev@gmail.com
License: New BSD License
Platform: UNKNOWN
Requires-Dist: matplotlib
Requires-Dist: numpy
Requires-Dist: scipy
Requires-Dist: six
